{
    "swagger": "2.0",
    "info": {
        "contact": {}
    },
    "paths": {
        "/api/Categoria/Create": {
            "post": {
                "consumes": [
                    "application/json"
                ],
                "produces": [
                    "application/json"
                ],
                "tags": [
                    "categorias"
                ],
                "summary": "Create a categoria",
                "parameters": [
                    {
                        "description": "Categoria data",
                        "name": "categoria",
                        "in": "body",
                        "required": true,
                        "schema": {
                            "$ref": "#/definitions/types.Categoria"
                        }
                    }
                ],
                "responses": {
                    "200": {
                        "description": "OK",
                        "schema": {
                            "$ref": "#/definitions/pkg.Body-types_Categoria"
                        }
                    }
                }
            }
        },
        "/api/Categoria/DeleteByID/{id}": {
            "post": {
                "consumes": [
                    "application/json"
                ],
                "produces": [
                    "application/json"
                ],
                "tags": [
                    "categorias"
                ],
                "summary": "Delete a categoria by ID",
                "parameters": [
                    {
                        "type": "integer",
                        "description": "categoria ID",
                        "name": "id",
                        "in": "path",
                        "required": true
                    }
                ],
                "responses": {
                    "200": {
                        "description": "OK",
                        "schema": {
                            "$ref": "#/definitions/pkg.Body-string"
                        }
                    }
                }
            }
        },
        "/api/Categoria/GetAll": {
            "get": {
                "consumes": [
                    "application/json"
                ],
                "produces": [
                    "application/json"
                ],
                "tags": [
                    "categorias"
                ],
                "summary": "Get categorias",
                "responses": {
                    "200": {
                        "description": "OK",
                        "schema": {
                            "$ref": "#/definitions/pkg.Body-array_types_Categoria"
                        }
                    }
                }
            }
        },
        "/api/Categoria/GetByID/{id}": {
            "get": {
                "consumes": [
                    "application/json"
                ],
                "produces": [
                    "application/json"
                ],
                "tags": [
                    "categorias"
                ],
                "summary": "Get categorias",
                "parameters": [
                    {
                        "type": "integer",
                        "description": "Categoria ID",
                        "name": "id",
                        "in": "path",
                        "required": true
                    }
                ],
                "responses": {
                    "200": {
                        "description": "OK",
                        "schema": {
                            "$ref": "#/definitions/pkg.Body-types_Categoria"
                        }
                    }
                }
            }
        },
        "/api/FormaPago/Create": {
            "post": {
                "consumes": [
                    "application/json"
                ],
                "produces": [
                    "application/json"
                ],
                "tags": [
                    "FormaPago"
                ],
                "summary": "Create a FormaPago",
                "parameters": [
                    {
                        "description": "FormaPago data",
                        "name": "FormaPago",
                        "in": "body",
                        "required": true,
                        "schema": {
                            "$ref": "#/definitions/types.FormaPago"
                        }
                    }
                ],
                "responses": {
                    "200": {
                        "description": "OK",
                        "schema": {
                            "$ref": "#/definitions/pkg.Body-types_FormaPago"
                        }
                    }
                }
            }
        },
        "/api/FormaPago/DeleteByID/{id}": {
            "post": {
                "consumes": [
                    "application/json"
                ],
                "produces": [
                    "application/json"
                ],
                "tags": [
                    "FormaPago"
                ],
                "summary": "Delete a FormaPago by ID",
                "parameters": [
                    {
                        "type": "integer",
                        "description": "FormaPago ID",
                        "name": "id",
                        "in": "path",
                        "required": true
                    }
                ],
                "responses": {
                    "200": {
                        "description": "OK",
                        "schema": {
                            "$ref": "#/definitions/pkg.Body-string"
                        }
                    }
                }
            }
        },
        "/api/FormaPago/GetAll": {
            "get": {
                "consumes": [
                    "application/json"
                ],
                "produces": [
                    "application/json"
                ],
                "tags": [
                    "FormaPago"
                ],
                "summary": "Get FormaPago",
                "responses": {
                    "200": {
                        "description": "OK",
                        "schema": {
                            "$ref": "#/definitions/pkg.Body-array_types_FormaPago"
                        }
                    }
                }
            }
        },
        "/api/FormaPago/GetByID/{id}": {
            "get": {
                "consumes": [
                    "application/json"
                ],
                "produces": [
                    "application/json"
                ],
                "tags": [
                    "FormaPago"
                ],
                "summary": "Get FormaPago",
                "parameters": [
                    {
                        "type": "integer",
                        "description": "FormaPago ID",
                        "name": "id",
                        "in": "path",
                        "required": true
                    }
                ],
                "responses": {
                    "200": {
                        "description": "OK",
                        "schema": {
                            "$ref": "#/definitions/pkg.Body-types_FormaPago"
                        }
                    }
                }
            }
        },
        "/api/Product/Create": {
            "post": {
                "consumes": [
                    "application/json"
                ],
                "produces": [
                    "application/json"
                ],
                "tags": [
                    "products"
                ],
                "summary": "Create a new product",
                "parameters": [
                    {
                        "description": "Product data",
                        "name": "product",
                        "in": "body",
                        "required": true,
                        "schema": {
                            "$ref": "#/definitions/types.Producto"
                        }
                    }
                ],
                "responses": {
                    "200": {
                        "description": "OK",
                        "schema": {
                            "$ref": "#/definitions/pkg.Body-types_Producto"
                        }
                    }
                }
            }
        },
        "/api/Product/DeleteByID/{id}": {
            "post": {
                "consumes": [
                    "application/json"
                ],
                "produces": [
                    "application/json"
                ],
                "tags": [
                    "products"
                ],
                "summary": "Delete a product by ID",
                "parameters": [
                    {
                        "type": "integer",
                        "description": "Product ID",
                        "name": "id",
                        "in": "path",
                        "required": true
                    }
                ],
                "responses": {
                    "200": {
                        "description": "OK",
                        "schema": {
                            "$ref": "#/definitions/pkg.Body-string"
                        }
                    }
                }
            }
        },
        "/api/Product/GetAll": {
            "get": {
                "consumes": [
                    "application/json"
                ],
                "produces": [
                    "application/json"
                ],
                "tags": [
                    "products"
                ],
                "summary": "Get all products",
                "responses": {
                    "200": {
                        "description": "OK",
                        "schema": {
                            "$ref": "#/definitions/pkg.Body-array_types_Producto"
                        }
                    }
                }
            }
        },
        "/api/Product/GetByID/{id}": {
            "get": {
                "consumes": [
                    "application/json"
                ],
                "produces": [
                    "application/json"
                ],
                "tags": [
                    "products"
                ],
                "summary": "Get a product by ID",
                "parameters": [
                    {
                        "type": "integer",
                        "description": "Product ID",
                        "name": "id",
                        "in": "path",
                        "required": true
                    }
                ],
                "responses": {
                    "200": {
                        "description": "OK",
                        "schema": {
                            "$ref": "#/definitions/pkg.Body-types_Producto"
                        }
                    }
                }
            }
        },
        "/api/Product/Update/{id}": {
            "post": {
                "consumes": [
                    "application/json"
                ],
                "produces": [
                    "application/json"
                ],
                "tags": [
                    "products"
                ],
                "summary": "Update a product",
                "parameters": [
                    {
                        "type": "integer",
                        "description": "Product ID",
                        "name": "id",
                        "in": "path",
                        "required": true
                    },
                    {
                        "description": "Product data",
                        "name": "product",
                        "in": "body",
                        "required": true,
                        "schema": {
                            "$ref": "#/definitions/types.Producto"
                        }
                    }
                ],
                "responses": {
                    "200": {
                        "description": "OK",
                        "schema": {
                            "$ref": "#/definitions/pkg.Body-types_Producto"
                        }
                    }
                }
            }
        },
        "/api/ProductComp/Create": {
            "post": {
                "consumes": [
                    "application/json"
                ],
                "produces": [
                    "application/json"
                ],
                "tags": [
                    "products"
                ],
                "summary": "Create a new productComp",
                "parameters": [
                    {
                        "description": "Product data",
                        "name": "product",
                        "in": "body",
                        "required": true,
                        "schema": {
                            "$ref": "#/definitions/dto.ProductoComp"
                        }
                    }
                ],
                "responses": {
                    "200": {
                        "description": "OK",
                        "schema": {
                            "$ref": "#/definitions/pkg.Body-types_ProductoCompuesto"
                        }
                    }
                }
            }
        },
        "/api/ProductComp/DeleteByID/{id}": {
            "post": {
                "consumes": [
                    "application/json"
                ],
                "produces": [
                    "application/json"
                ],
                "tags": [
                    "products"
                ],
                "summary": "Delete a productComp by ID",
                "parameters": [
                    {
                        "type": "integer",
                        "description": "Product ID",
                        "name": "id",
                        "in": "path",
                        "required": true
                    }
                ],
                "responses": {
                    "200": {
                        "description": "OK",
                        "schema": {
                            "$ref": "#/definitions/pkg.Body-string"
                        }
                    }
                }
            }
        },
        "/api/ProductComp/GetAll": {
            "get": {
                "consumes": [
                    "application/json"
                ],
                "produces": [
                    "application/json"
                ],
                "tags": [
                    "products"
                ],
                "summary": "Get all products",
                "responses": {
                    "200": {
                        "description": "OK",
                        "schema": {
                            "$ref": "#/definitions/pkg.Body-array_types_ProductoCompuesto"
                        }
                    }
                }
            }
        },
        "/api/ProductComp/GetByID/{id}": {
            "get": {
                "consumes": [
                    "application/json"
                ],
                "produces": [
                    "application/json"
                ],
                "tags": [
                    "products"
                ],
                "summary": "Get a product by ID",
                "parameters": [
                    {
                        "type": "integer",
                        "description": "Product ID",
                        "name": "id",
                        "in": "path",
                        "required": true
                    }
                ],
                "responses": {
                    "200": {
                        "description": "OK",
                        "schema": {
                            "$ref": "#/definitions/pkg.Body-dto_ProductoComp"
                        }
                    }
                }
            }
        },
        "/api/Sucursal/Create": {
            "post": {
                "consumes": [
                    "application/json"
                ],
                "produces": [
                    "application/json"
                ],
                "tags": [
                    "Sucursal"
                ],
                "summary": "Create a new sucursal",
                "parameters": [
                    {
                        "description": "Sucursal data",
                        "name": "product",
                        "in": "body",
                        "required": true,
                        "schema": {
                            "$ref": "#/definitions/types.Sucursal"
                        }
                    }
                ],
                "responses": {
                    "200": {
                        "description": "OK",
                        "schema": {
                            "$ref": "#/definitions/pkg.Body-types_Sucursal"
                        }
                    }
                }
            }
        },
        "/api/Sucursal/DeleteByID/{id}": {
            "post": {
                "consumes": [
                    "application/json"
                ],
                "produces": [
                    "application/json"
                ],
                "tags": [
                    "Sucursal"
                ],
                "summary": "Delete a sucursal by ID",
                "parameters": [
                    {
                        "type": "integer",
                        "description": "Sucursal ID",
                        "name": "id",
                        "in": "path",
                        "required": true
                    }
                ],
                "responses": {
                    "200": {
                        "description": "OK",
                        "schema": {
                            "$ref": "#/definitions/pkg.Body-string"
                        }
                    }
                }
            }
        },
        "/api/Sucursal/GetAll": {
            "get": {
                "consumes": [
                    "application/json"
                ],
                "produces": [
                    "application/json"
                ],
                "tags": [
                    "Sucursal"
                ],
                "summary": "Get all Sucursales",
                "responses": {
                    "200": {
                        "description": "OK",
                        "schema": {
                            "$ref": "#/definitions/pkg.Body-array_types_Sucursal"
                        }
                    }
                }
            }
        },
        "/api/Sucursal/GetByID/{id}": {
            "get": {
                "consumes": [
                    "application/json"
                ],
                "produces": [
                    "application/json"
                ],
                "tags": [
                    "Sucursal"
                ],
                "summary": "Get a sucursal by ID",
                "parameters": [
                    {
                        "type": "integer",
                        "description": "Sucursal ID",
                        "name": "id",
                        "in": "path",
                        "required": true
                    }
                ],
                "responses": {
                    "200": {
                        "description": "OK",
                        "schema": {
                            "$ref": "#/definitions/pkg.Body-types_Sucursal"
                        }
                    }
                }
            }
        },
        "/api/Sucursal/Update/{id}": {
            "post": {
                "consumes": [
                    "application/json"
                ],
                "produces": [
                    "application/json"
                ],
                "tags": [
                    "Sucursal"
                ],
                "summary": "Update a sucursal",
                "parameters": [
                    {
                        "type": "integer",
                        "description": "Sucursal ID",
                        "name": "id",
                        "in": "path",
                        "required": true
                    },
                    {
                        "description": "Sucursal data",
                        "name": "product",
                        "in": "body",
                        "required": true,
                        "schema": {
                            "$ref": "#/definitions/types.Sucursal"
                        }
                    }
                ],
                "responses": {
                    "200": {
                        "description": "OK",
                        "schema": {
                            "$ref": "#/definitions/pkg.Body-types_Sucursal"
                        }
                    }
                }
            }
        }
    },
    "definitions": {
        "dto.ProductoComp": {
            "type": "object",
            "properties": {
                "id": {
                    "type": "integer"
                },
                "productoComponenteID": {
                    "type": "integer"
                },
                "productoPrincipalID": {
                    "type": "integer"
                }
            }
        },
        "pkg.Body-array_types_Categoria": {
            "type": "object",
            "properties": {
                "data": {
                    "type": "array",
                    "items": {
                        "$ref": "#/definitions/types.Categoria"
                    }
                }
            }
        },
        "pkg.Body-array_types_FormaPago": {
            "type": "object",
            "properties": {
                "data": {
                    "type": "array",
                    "items": {
                        "$ref": "#/definitions/types.FormaPago"
                    }
                }
            }
        },
        "pkg.Body-array_types_Producto": {
            "type": "object",
            "properties": {
                "data": {
                    "type": "array",
                    "items": {
                        "$ref": "#/definitions/types.Producto"
                    }
                }
            }
        },
        "pkg.Body-array_types_ProductoCompuesto": {
            "type": "object",
            "properties": {
                "data": {
                    "type": "array",
                    "items": {
                        "$ref": "#/definitions/types.ProductoCompuesto"
                    }
                }
            }
        },
        "pkg.Body-array_types_Sucursal": {
            "type": "object",
            "properties": {
                "data": {
                    "type": "array",
                    "items": {
                        "$ref": "#/definitions/types.Sucursal"
                    }
                }
            }
        },
        "pkg.Body-dto_ProductoComp": {
            "type": "object",
            "properties": {
                "data": {
                    "$ref": "#/definitions/dto.ProductoComp"
                }
            }
        },
        "pkg.Body-string": {
            "type": "object",
            "properties": {
                "data": {
                    "type": "string"
                }
            }
        },
        "pkg.Body-types_Categoria": {
            "type": "object",
            "properties": {
                "data": {
                    "$ref": "#/definitions/types.Categoria"
                }
            }
        },
        "pkg.Body-types_FormaPago": {
            "type": "object",
            "properties": {
                "data": {
                    "$ref": "#/definitions/types.FormaPago"
                }
            }
        },
        "pkg.Body-types_Producto": {
            "type": "object",
            "properties": {
                "data": {
                    "$ref": "#/definitions/types.Producto"
                }
            }
        },
        "pkg.Body-types_ProductoCompuesto": {
            "type": "object",
            "properties": {
                "data": {
                    "$ref": "#/definitions/types.ProductoCompuesto"
                }
            }
        },
        "pkg.Body-types_Sucursal": {
            "type": "object",
            "properties": {
                "data": {
                    "$ref": "#/definitions/types.Sucursal"
                }
            }
        },
        "types.Categoria": {
            "type": "object",
            "properties": {
                "id": {
                    "type": "integer"
                },
                "nombre": {
                    "type": "string"
                }
            }
        },
        "types.FormaPago": {
            "type": "object",
            "properties": {
                "id": {
                    "type": "integer"
                },
                "nombre": {
                    "type": "string"
                }
            }
        },
        "types.Producto": {
            "type": "object",
            "properties": {
                "categoriaID": {
                    "type": "integer"
                },
                "id": {
                    "type": "integer"
                },
                "imagen": {
                    "type": "string"
                },
                "nombre": {
                    "type": "string"
                },
                "precio": {
                    "type": "number"
                },
                "stock": {
                    "type": "boolean"
                }
            }
        },
        "types.ProductoCompuesto": {
            "type": "object",
            "properties": {
                "id": {
                    "type": "integer"
                },
                "productoComponente": {
                    "$ref": "#/definitions/types.Producto"
                },
                "productoComponenteID": {
                    "type": "integer"
                },
                "productoPrincipal": {
                    "$ref": "#/definitions/types.Producto"
                },
                "productoPrincipalID": {
                    "type": "integer"
                }
            }
        },
        "types.Sucursal": {
            "type": "object",
            "properties": {
                "activo": {
                    "type": "boolean"
                },
                "direccion": {
                    "type": "string"
                },
                "id": {
                    "type": "integer"
                },
                "nombre": {
                    "type": "string"
                },
                "telefono": {
                    "type": "string"
                }
            }
        }
    }
}